sslserver/__init__.py
sslserver/certs/development.crt
sslserver/certs/development.key
sslserver/management/__init__.py
sslserver/management/commands/__init__.py
sslserver/management/commands/runsslserver.py
django_sslserver_v2-1.0.dist-info/AUTHORS
django_sslserver_v2-1.0.dist-info/LICENSE
django_sslserver_v2-1.0.dist-info/METADATA
django_sslserver_v2-1.0.dist-info/WHEEL
django_sslserver_v2-1.0.dist-info/top_level.txt
django_sslserver_v2-1.0.dist-info/RECORD
