Metadata-Version: 2.1
Name: django-sslserver-v2
Version: 1.0
Summary: An SSL-enabled development server for Django. Supports latest versions of Django and Python
Author-email: Shashwat <shashwat13.8@gmail.com>
License: MIT
Keywords: django-sslserver,sslserver
Classifier: Environment :: Web Environment
Classifier: License :: OSI Approved :: MIT License
Classifier: Operating System :: OS Independent
Classifier: Programming Language :: Python
Classifier: Programming Language :: Python :: 2
Classifier: Programming Language :: Python :: 2.7
Classifier: Programming Language :: Python :: 3
Classifier: Programming Language :: Python :: 3.4
Classifier: Programming Language :: Python :: 3.5
Classifier: Programming Language :: Python :: 3.6
Classifier: Programming Language :: Python :: 3.7
Classifier: Programming Language :: Python :: 3.10
Classifier: Programming Language :: Python :: 3.12
Classifier: Framework :: Django
Classifier: Framework :: Django :: 1.8
Classifier: Framework :: Django :: 1.9
Classifier: Framework :: Django :: 1.10
Classifier: Framework :: Django :: 1.11
Classifier: Framework :: Django :: 2.0
Classifier: Framework :: Django :: 2.1
Classifier: Framework :: Django :: 2.2
Classifier: Framework :: Django :: 4.0
Classifier: Framework :: Django :: 4.2
Requires-Python: >=2
License-File: LICENSE
License-File: AUTHORS
Requires-Dist: Django>=1.8
